[
    {
        "id": 110,
        "item_name": "Wireless Bluetooth Headphones",
        "image_url": "https://www.jlab.com/cdn/shop/files/1JBudsLuxGraphite_c6f0cdf2-c75c-4cf9-ac0a-b44fbb11fc4b.jpg?v=1719941098&width=256",
        "price": "79.99",
        "quantity": 150,
        "description": "Noise-cancelling headphones with great sound quality."
    },
    {
        "id": 111,
        "item_name": "Smartwatch",
        "image_url": "https://helios-i.mashable.com/imagery/articles/00TIS6MAKw1iMyViYY1hM1x/images-1.fill.size_256x256.v1723738846.png",
        "price": "199.99",
        "quantity": 200,
        "description": "Track your fitness and stay connected on the go."
    },
    {
        "id": 112,
        "item_name": "Portable Charger",
        "image_url": "https://www.jumpplus.com/web/image/product.template/29155/image_256/%5BNBCPC10KPDGRY%5D%20Nimble%20CHAMP%2010%2C000%20mAh%20Portable%20Charger%2018W%20-%20Charcoal?unique=a9946ba",
        "price": "29.99",
        "quantity": 300,
        "description": "High-capacity power bank for your devices."
    },
    {
        "id": 113,
        "item_name": "Instant Camera",
        "image_url": "https://www.dealsmagnet.com/images/polaroid-now-2nd-generation-i-type-camera-9130-l-1asuJgiq.jpg",
        "price": "89.99",
        "quantity": 100,
        "description": "Capture moments with this easy-to-use instant camera."
    },
    {
        "id": 114,
        "item_name": "Electric Toothbrush",
        "image_url": "https://www.net32.com/cdn-cgi/image/dpr=2,,width=128,/media/shared/common/mp/procter-gamble/oral-b-vitality/media/80286467.jpg",
        "price": "49.99",
        "quantity": 250,
        "description": "Rechargeable toothbrush with multiple settings."
    },
    {
        "id": 115,
        "item_name": "Yoga Mat",
        "image_url": "https://www.olympiasouq.com/web/image/product.template/25224/image_256",
        "price": "24.99",
        "quantity": 400,
        "description": "Non-slip yoga mat for your home workouts."
    },
    {
        "id": 116,
        "item_name": "Water Bottle",
        "image_url": "https://cdn.shoplightspeed.com/shops/602795/files/64192148/image.jpg",
        "price": "19.99",
        "quantity": 500,
        "description": "Eco-friendly reusable water bottle."
    },
    {
        "id": 117,
        "item_name": "Wireless Mouse",
        "image_url": "https://www.jlab.com/cdn/shop/files/JBudsMouse5-min.jpg?v=1719941108&width=256",
        "price": "29.99",
        "quantity": 350,
        "description": "Ergonomic wireless mouse for comfortable use."
    },
    {
        "id": 118,
        "item_name": "Gaming Keyboard",
        "image_url": "https://cdna.pcpartpicker.com/static/forever/images/product/72afebab92f6ad28ba42d28c64442a07.256p.jpg",
        "price": "89.99",
        "quantity": 120,
        "description": "Mechanical keyboard with customizable RGB lighting."
    },
    {
        "id": 119,
        "item_name": "Fitness Tracker",
        "image_url": "https://helios-i.mashable.com/imagery/articles/06YqRhH21vP5f1ja8SAsKwv/images-5.fill.size_256x256.v1721265310.png",
        "price": "59.99",
        "quantity": 250,
        "description": "Monitor your heart rate and activity levels."
    },
    {
        "id": 120,
        "item_name": "Leather Wallet",
        "image_url": "https://eu-images.contentstack.com/v3/assets/blt7dcd2cfbc90d45de/blte7535a188fc57c2a/60dbb1e0c5c41538a15436db/2_289.jpg?format=pjpg&auto=webp&quality=75%2C90&width=256",
        "price": "39.99",
        "quantity": 200,
        "description": "Classic leather wallet with multiple card slots."
    },
    {
        "id": 121,
        "item_name": "Coffee Maker",
        "image_url": "https://ip.prod.freshop.retail.ncrcloud.com/resize?url=https://images.freshop.ncrcloud.com/00611247373064/6d0613e45744fe311d7e2d77e6c81653_large.png&width=256&type=webp&quality=80",
        "price": "129.99",
        "quantity": 80,
        "description": "Brew your favorite coffee at home."
    },
    {
        "id": 122,
        "item_name": "Bluetooth Speaker",
        "image_url": "https://exceldisc.com/_next/image?url=https%3A%2F%2Fapiv2.exceldisc.com%2Fmedia%2F8309%2Fconversions%2Fultimate-ears-megaboom-3-portable-bluetooth-speaker-night-black-preview.jpg&w=256&q=75",
        "price": "49.99",
        "quantity": 150,
        "description": "Portable speaker with high-quality sound."
    },
    {
        "id": 123,
        "item_name": "Kindle E-Reader",
        "image_url": "https://helios-i.mashable.com/imagery/reviews/06d50WrKklnWD1uZ9IpfHAm/images-112.fill.size_256x256.v1720804413.png",
        "price": "89.99",
        "quantity": 100,
        "description": "Lightweight e-reader for book lovers."
    },
    {
        "id": 124,
        "item_name": "Wireless Charger",
        "image_url": "https://static.prod.middleware.zagg.com/_next/image?url=https://cdn11.bigcommerce.com/s-uv4dd6xvbk/images/stencil/380x380/products/2504/8162/Hero_2__35508.1704756672.jpg?c=1?c=1&w=256&q=90&fm=webp",
        "price": "39.99",
        "quantity": 200,
        "description": "Fast wireless charging for your devices."
    },
    {
        "id": 125,
        "item_name": "Travel Backpack",
        "image_url": "https://saraemart.com/_next/image?url=https%3A%2F%2Fprod.saraemart.com%2FImages%2FProducts%2FVariationWisetImage%2F8e78d18c12b947ccba1d1c9ee3579d75.jpeg&w=256&q=75",
        "price": "69.99",
        "quantity": 120,
        "description": "Durable backpack perfect for travelers."
    },
    {
        "id": 126,
        "item_name": "Potted Plant",
        "image_url": "https://public.blenderkit.com/thumbnails/assets/7a00fde274bd46f493f8ef6b5c088899/files/thumbnail_2dcbcc8c-09ec-4e77-b011-113cafec06f5.jpg.256x256_q85.jpg.webp?webp_generated=1612170777",
        "price": "24.99",
        "quantity": 300,
        "description": "Add greenery to your home or office."
    },
    {
        "id": 127,
        "item_name": "Smart Light Bulb",
        "image_url": "https://helios-i.mashable.com/imagery/articles/01hrpirroH3XEftPqH7Rca7/images-1.fill.size_256x256.v1722437637.png",
        "price": "19.99",
        "quantity": 400,
        "description": "Control your lighting with your smartphone."
    },
    {
        "id": 128,
        "item_name": "Bluetooth Headset",
        "image_url": "https://www.jlab.com/cdn/shop/files/JBudsWork1.jpg?v=1719941103&width=256",
        "price": "59.99",
        "quantity": 150,
        "description": "Comfortable headset for hands-free calls."
    },
    {
        "id": 129,
        "item_name": "HDMI Cable",
        "image_url": "https://www.ufprentals.com/static/db/hdmicable.jpg",
        "price": "14.99",
        "quantity": 500,
        "description": "High-speed HDMI cable for your devices."
    },
    {
        "id": 130,
        "item_name": "Drone with Camera",
        "image_url": "https://helios-i.mashable.com/imagery/articles/03AYlCWPrWKf6bjUVJCPDIg/images-1.fill.size_256x256.v1728462135.png",
        "price": "299.99",
        "quantity": 75,
        "description": "Capture stunning aerial photos and videos."
    },
    {
        "id": 131,
        "item_name": "Electric Kettle",
        "image_url": "https://m.media-amazon.com/images/I/71qe2yC4KDL._UC256,256_CACC,256,256_.jpg",
        "price": "39.99",
        "quantity": 250,
        "description": "Quickly boil water for tea or coffee."
    },
    {
        "id": 132,
        "item_name": "Bluetooth Tracker",
        "image_url": "https://helios-i.mashable.com/imagery/articles/00eaFrVy6HZBnDhkTDeYuBr/images-1.fill.size_256x256.v1670516702.png",
        "price": "24.99",
        "quantity": 400,
        "description": "Never lose your belongings again."
    },
    {
        "id": 133,
        "item_name": "Noise-Canceling Earbuds",
        "image_url": "https://www.jlab.com/cdn/shop/files/1_Flex_Open_Black_6dd8f5f0-a6c5-43bd-bccc-949d0f9fe2c3.jpg?v=1719941145&width=256",
        "price": "89.99",
        "quantity": 150,
        "description": "Immerse yourself in your music."
    }
]